pytest_testrail_appetize
