Metadata-Version: 1.1
Name: pytest-testrail-appetize
Version: 1.0.2
Summary: pytest plugin for creating TestRail runs and adding results
Home-page: https://github.com/AppetizeAutomation/pytest-testrail
Author: Appetize
Author-email: chris.williams@appetize.com
License: UNKNOWN
Download-URL: https://github.com/AppetizeAutomation/pytest-testrail/archive/refs/tags/v1.0.2.tar.gz
Platform: UNKNOWN
